netdot/__init__.py
netdot/client.py
netdot/csv_util.py
netdot/defaults.py
netdot/exceptions.py
netdot/io.py
netdot/mac_address.py
netdot/parse.py
netdot/repository.py
netdot/trace.py
netdot/utils.py
netdot/validate.py
netdot/dataclasses/__init__.py
netdot/dataclasses/asset.py
netdot/dataclasses/base.py
netdot/dataclasses/cables.py
netdot/dataclasses/device.py
netdot/dataclasses/dns.py
netdot/dataclasses/fwtable.py
netdot/dataclasses/interface.py
netdot/dataclasses/ipblock.py
netdot/dataclasses/physaddr.py
netdot/dataclasses/products.py
netdot/dataclasses/site.py
netdot/dataclasses/vlan.py
netdot-0.3.2.dist-info/METADATA
netdot-0.3.2.dist-info/WHEEL
netdot-0.3.2.dist-info/licenses/LICENSE
netdot-0.3.2.dist-info/RECORD
