Metadata-Version: 2.1
Name: netdot
Version: 0.3.2
Summary: Python wrapper for Netdot Web API.
Author-email: University of Oregon <ntsjenkins@uoregon.edu>
License-File: LICENSE
Keywords: API,IPAM,NTS,REST,UO,VRA,netdot
Classifier: Development Status :: 3 - Alpha
Classifier: Intended Audience :: Developers
Classifier: License :: OSI Approved :: MIT License
Classifier: Programming Language :: Python :: 3.8
Requires-Dist: configargparse<2,>=1
Requires-Dist: humanize>=2
Requires-Dist: pathvalidate<3,>=2
Requires-Dist: requests<3,>=2
Requires-Dist: tabulate>=0.8
Requires-Dist: uologging>=0.7.0
